Workbook

Sheet 00_README
A1: PRICING TEMPLATE - README
A3: PURPOSE
A4: This workbook translates the hours estimate from doc 16 into a priced engagement using
A5: the rate-card structure from doc 19. Update yellow cells to fit your engagement.
A7: WORKBOOK STRUCTURE
A8: 01_RateCard Per-role x per-geography rates (YELLOW = edit)
A9: 02_HoursByPhase Hours per role per phase + geography assignment (YELLOW = edit)
A10: 03_CalculatedCost Auto: hours x rate per phase (GRAY = formula; RED = internal)
A11: 04_Discounts Discount triggers + percentages (YELLOW = edit; INTERNAL)
A12: 05_RiskMargin Risk markup per phase + margin per role (YELLOW = edit; INTERNAL)
A13: 06_Summary Client-facing phase totals + Year-1/Year-2 rollup
A15: COLOR LEGEND
... A37: docs/19-pricing-model.md - this file's narrative companion

Sheet 01_RateCard
A1: ROLE / SENIORITY RATE CARD
A2: Fill in hourly rates per role/seniority/geography. Yellow cells = edit. Replace '<RATE>' placeholders with your firm's actual rates (in your chosen currency). Used by sheet 03_CalculatedCost.
A4: Role | B4: Seniority | C4: Onshore | D4: Nearshore | E4: Offshore
A5: Solution Architect | B5: Principal | C5: <RATE> | D5: <RATE> | E5: <RATE>
A6: Integration Lead Engineer | B6: Senior | C6: <RATE> | D6: <RATE> | E6: <RATE>
A7: Integration Engineer | B7: Mid | C7: <RATE> | D7: <RATE> | E7: <RATE>
A8: Integration Engineer | B8: Junior | C8: <RATE> | D8: <RATE> | E8: <RATE>
A9: DevOps / SRE Engineer | B9: Senior | C9: <RATE> | D9: <RATE> | E9: <RATE>
A10: DevOps / SRE Engineer | B10: Mid | C10: <RATE> | D10: <RATE> | E10: <RATE>
A11: Security Engineer | B11: Senior | C11: <RATE> | D11: <RATE> | E11: <RATE>
A12: Project Manager | B12: Senior | C12: <RATE> | D12: <RATE> | E12: <RATE>
A13: Technical Writer | B13: Mid | C13: <RATE> | D13: <RATE> | E13: <RATE>
A16: Legend:
A17: Yellow = edit this cell
A18: Gray = formula-driven (do not edit)
A19: Red = INTERNAL-ONLY (do not share with client)

Sheet 02_HoursByPhase
A1: HOURS BY PHASE (per role/seniority)
A2: Yellow cells = edit hours per engagement. Column C selects geography (Onshore / Nearshore / Offshore) - drives rate lookup. Default hours pre-filled from doc 16. Adjust if engagement scope deviates.
A4: Role | B4: Seniority | C4: Geography | D4: Phase 1 - Discovery | E4: Phase 2 - Foundation | F4: Phase 3 - First-Wave APIs | G4: Phase 4 - Hypercare | H4: Steady-state (per month) | I4: Annual Recurring (per year)
A5: Solution Architect | B5: Principal | C5: Onshore | D5: 108 | E5: 384 | F5: 200 | G5: 64 | H5: 13 | I5: 40
A6: Integration Lead Engineer | B6: Senior | C6: Onshore | D6: 36 | E6: 768 | F6: 600 | G6: 192 | H6: 39 | I6: 60
A7: Integration Engineer | B7: Mid | C7: Onshore | D7: 0 | E7: 320 | F7: 700 | G7: 96 | H7: 26 | I7: 30
A8: Integration Engineer | B8: Junior | C8: Onshore | D8: 0 | E8: 160 | F8: 350 | G8: 96 | H8: 13 | I8: 20
A9: DevOps / SRE Engineer | B9: Senior | C9: Onshore | D9: 18 | E9: 384 | F9: 100 | G9: 128 | H9: 18 | I9: 40
A10: DevOps / SRE Engineer | B10: Mid | C10: Onshore | D10: 0 | E10: 192 | F10: 50 | G10: 64 | H10: 8 | I10: 20
A11: Security Engineer | B11: Senior | C11: Onshore | D11: 18 | E11: 240 | F11: 100 | G11: 32 | H11: 13 | I11: 80
A12: Project Manager | B12: Senior | C12: Onshore | D12: 36 | E12: 144 | F12: 150 | G12: 64 | H12: 13 | I12: 24
A13: Technical Writer | B13: Mid | C13: Onshore | D13: 0 | E13: 96 | F13: 50 | G13: 64 | H13: 6 | I13: 16
A14: TOTAL | D14: =SUM(D5:D13) | E14: =SUM(E5:E13) | F14: =SUM(F5:F13) | G14: =SUM(G5:G13) | H14: =SUM(H5:H13) | I14: =SUM(I5:I13)

Sheet 03_CalculatedCost
A1: CALCULATED COST (auto-computed) - INTERNAL ONLY
A2: Auto-computed: hours from 02_HoursByPhase x rates from 01_RateCard. Do not edit cells. Do not share this sheet externally - it reveals rate buildup.
A4: Role | B4: Seniority | C4: Rate (looked up) | D4: Phase 1 - Discovery | E4: Phase 2 - Foundation | F4: Phase 3 - First-Wave APIs | G4: Phase 4 - Hypercare | H4: Steady-state (per month) | I4: Annual Recurring (per year)
A5: Solution Architect | B5: Principal | C5: =IFERROR(INDEX('01_RateCard'!$C$5:$E$5,MATCH('02_HoursByPhase'!C5,'01_RateCard'!$C$4:$E$4,0)),"<set rate>") | D5: =IFERROR('02_HoursByPhase'!D5*$C5,0) | E5: =IFERROR('02_HoursByPhase'!E5*$C5,0) | F5: =IFERROR('02_HoursByPhase'!F5*$C5,0) | G5: =IFERROR('02_HoursByPhase'!G5*$C5,0) | H5: =IFERROR('02_HoursByPhase'!H5*$C5,0) | I5: =IFERROR('02_HoursByPhase'!I5*$C5,0)
A6: Integration Lead Engineer | B6: Senior | C6: =IFERROR(INDEX('01_RateCard'!$C$6:$E$6,MATCH('02_HoursByPhase'!C6,'01_RateCard'!$C$4:$E$4,0)),"<set rate>") | D6: =IFERROR('02_HoursByPhase'!D6*$C6,0) | E6: =IFERROR('02_HoursByPhase'!E6*$C6,0) | F6: =IFERROR('02_HoursByPhase'!F6*$C6,0) | G6: =IFERROR('02_HoursByPhase'!G6*$C6,0) | H6: =IFERROR('02_HoursByPhase'!H6*$C6,0) | I6: =IFERROR('02_HoursByPhase'!I6*$C6,0)
A7: Integration Engineer | B7: Mid | C7: =IFERROR(INDEX('01_RateCard'!$C$7:$E$7,MATCH('02_HoursByPhase'!C7,'01_RateCard'!$C$4:$E$4,0)),"<set rate>") | D7: =IFERROR('02_HoursByPhase'!D7*$C7,0) | E7: =IFERROR('02_HoursByPhase'!E7*$C7,0) | F7: =IFERROR('02_HoursByPhase'!F7*$C7,0) | G7: =IFERROR('02_HoursByPhase'!G7*$C7,0) | H7: =IFERROR('02_HoursByPhase'!H7*$C7,0) | I7: =IFERROR('02_HoursByPhase'!I7*$C7,0)
A8: Integration Engineer | B8: Junior | C8: =IFERROR(INDEX('01_RateCard'!$C$8:$E$8,MATCH('02_HoursByPhase'!C8,'01_RateCard'!$C$4:$E$4,0)),"<set rate>") | D8: =IFERROR('02_HoursByPhase'!D8*$C8,0) | E8: =IFERROR('02_HoursByPhase'!E8*$C8,0) | F8: =IFERROR('02_HoursByPhase'!F8*$C8,0) | G8: =IFERROR('02_HoursByPhase'!G8*$C8,0) | H8: =IFERROR('02_HoursByPhase'!H8*$C8,0) | I8: =IFERROR('02_HoursByPhase'!I8*$C8,0)
A9: DevOps / SRE Engineer | B9: Senior | C9: =IFERROR(INDEX('01_RateCard'!$C$9:$E$9,MATCH('02_HoursByPhase'!C9,'01_RateCard'!$C$4:$E$4,0)),"<set rate>") | D9: =IFERROR('02_HoursByPhase'!D9*$C9,0) | E9: =IFERROR('02_HoursByPhase'!E9*$C9,0) | F9: =IFERROR('02_HoursByPhase'!F9*$C9,0) | G9: =IFERROR('02_HoursByPhase'!G9*$C9,0) | H9: =IFERROR('02_HoursByPhase'!H9*$C9,0) | I9: =IFERROR('02_HoursByPhase'!I9*$C9,0)
A10: DevOps / SRE Engineer | B10: Mid | C10: =IFERROR(INDEX('01_RateCard'!$C$10:$E$10,MATCH('02_HoursByPhase'!C10,'01_RateCard'!$C$4:$E$4,0)),"<set rate>") | D10: =IFERROR('02_HoursByPhase'!D10*$C10,0) | E10: =IFERROR('02_HoursByPhase'!E10*$C10,0) | F10: =IFERROR('02_HoursByPhase'!F10*$C10,0) | G10: =IFERROR('02_HoursByPhase'!G10*$C10,0) | H10: =IFERROR('02_HoursByPhase'!H10*$C10,0) | I10: =IFERROR('02_HoursByPhase'!I10*$C10,0)
A11: Security Engineer | B11: Senior | C11: =IFERROR(INDEX('01_RateCard'!$C$11:$E$11,MATCH('02_HoursByPhase'!C11,'01_RateCard'!$C$4:$E$4,0)),"<set rate>") | D11: =IFERROR('02_HoursByPhase'!D11*$C11,0) | E11: =IFERROR('02_HoursByPhase'!E11*$C11,0) | F11: =IFERROR('02_HoursByPhase'!F11*$C11,0) | G11: =IFERROR('02_HoursByPhase'!G11*$C11,0) | H11: =IFERROR('02_HoursByPhase'!H11*$C11,0) | I11: =IFERROR('02_HoursByPhase'!I11*$C11,0)
A12: Project Manager | B12: Senior | C12: =IFERROR(INDEX('01_RateCard'!$C$12:$E$12,MATCH('02_HoursByPhase'!C12,'01_RateCard'!$C$4:$E$4,0)),"<set rate>") | D12: =IFERROR('02_HoursByPhase'!D12*$C12,0) | E12: =IFERROR('02_HoursByPhase'!E12*$C12,0) | F12: =IFERROR('02_HoursByPhase'!F12*$C12,0) | G12: =IFERROR('02_HoursByPhase'!G12*$C12,0) | H12: =IFERROR('02_HoursByPhase'!H12*$C12,0) | I12: =IFERROR('02_HoursByPhase'!I12*$C12,0)
A13: Technical Writer | B13: Mid | C13: =IFERROR(INDEX('01_RateCard'!$C$13:$E$13,MATCH('02_HoursByPhase'!C13,'01_RateCard'!$C$4:$E$4,0)),"<set rate>") | D13: =IFERROR('02_HoursByPhase'!D13*$C13,0) | E13: =IFERROR('02_HoursByPhase'!E13*$C13,0) | F13: =IFERROR('02_HoursByPhase'!F13*$C13,0) | G13: =IFERROR('02_HoursByPhase'!G13*$C13,0) | H13: =IFERROR('02_HoursByPhase'!H13*$C13,0) | I13: =IFERROR('02_HoursByPhase'!I13*$C13,0)
A14: SUBTOTAL (pre-discount, pre-margin) | D14: =SUM(D5:D13) | E14: =SUM(E5:E13) | F14: =SUM(F5:F13) | G14: =SUM(G5:G13) | H14: =SUM(H5:H13) | I14: =SUM(I5:I13)

Sheet 04_Discounts
A1: DISCOUNTS - INTERNAL ONLY
A2: Set discount % per type IF the trigger applies to this engagement. Discount cells are yellow (edit). Aggregate discount in green is formula-driven.
A4: Discount Type | B4: Trigger Description | C4: Applies? (Y/N) | D4: Discount %
A5: Volume / multi-year | B5: Engagement total > threshold OR multi-year commit | C5: N | D5: 0
A6: Retainer commitment | B6: 12-month retainer signed | C6: N | D6: 0
A7: Multi-engagement / framework | B7: Master agreement covering multiple projects | C7: N | D7: 0
A8: Pre-payment | B8: Quarterly or annual pre-payment | C8: N | D8: 0
A9: Reference / case-study | B9: Client agrees to be case study | C9: N | D9: 0
A10: Beta / first-of-its-kind | B10: Novel methodology, risk-sharing | C10: N | D10: 0
A11: Other (named in SOW) | B11: Custom discount with named justification | C11: N | D11: 0
A13: AGGREGATE DISCOUNT (sum of applies=Y) | D13: =SUMPRODUCT((C5:C11="Y")*D5:D11)

Sheet 05_RiskMargin
A1: RISK + MARGIN - INTERNAL ONLY
A2: Risk markup is applied per phase to fixed-bid phases especially. Margin % is per role (not used in summary calc - shown for transparency).
A4: RISK MARKUP PER PHASE
A5: Phase | B5: Risk Markup %
A6: Phase 1 - Discovery | B6: 0.05
A7: Phase 2 - Foundation | B7: 0.15
A8: Phase 3 - First-Wave APIs | B8: 0.08
A9: Phase 4 - Hypercare | B9: 0.1
A10: Steady-state (per month) | B10: 0.03
A11: Annual Recurring (per year) | B11: 0.05
A13: MARGIN % PER ROLE (informational)
A14: Role | B14: Seniority | C14: Margin %
A15: Solution Architect | B15: Principal | C15: 0.5
A16: Integration Lead Engineer | B16: Senior | C16: 0.4
A17: Integration Engineer | B17: Mid | C17: 0.3
A18: Integration Engineer | B18: Junior | C18: 0.25
A19: DevOps / SRE Engineer | B19: Senior | C19: 0.4
A20: DevOps / SRE Engineer | B20: Mid | C20: 0.3
A21: Security Engineer | B21: Senior | C21: 0.45
A22: Project Manager | B22: Senior | C22: 0.3
A23: Technical Writer | B23: Mid | C23: 0.25

Sheet 06_Summary
A1: CLIENT-FACING SUMMARY
A2: Phase-level totals. Safe to share with client. Numbers pull from other sheets - do not edit cells here directly.
A4: Phase | B4: Total Hours | C4: Subtotal Cost | D4: After Discount | E4: After Risk Markup | F4: FINAL
A5: Phase 1 - Discovery | B5: ='02_HoursByPhase'!D14 | C5: ='03_CalculatedCost'!D14 | D5: =C5*(1-'04_Discounts'!$D$13) | E5: =D5*(1+'05_RiskMargin'!$B$6) | F5: =E5
A6: Phase 2 - Foundation | B6: ='02_HoursByPhase'!E14 | C6: ='03_CalculatedCost'!E14 | D6: =C6*(1-'04_Discounts'!$D$13) | E6: =D6*(1+'05_RiskMargin'!$B$7) | F6: =E6
A7: Phase 3 - First-Wave APIs | B7: ='02_HoursByPhase'!F14 | C7: ='03_CalculatedCost'!F14 | D7: =C7*(1-'04_Discounts'!$D$13) | E7: =D7*(1+'05_RiskMargin'!$B$8) | F7: =E7
A8: Phase 4 - Hypercare | B8: ='02_HoursByPhase'!G14 | C8: ='03_CalculatedCost'!G14 | D8: =C8*(1-'04_Discounts'!$D$13) | E8: =D8*(1+'05_RiskMargin'!$B$9) | F8: =E8
A9: Steady-state (per month) | B9: ='02_HoursByPhase'!H14 | C9: ='03_CalculatedCost'!H14 | D9: =C9*(1-'04_Discounts'!$D$13) | E9: =D9*(1+'05_RiskMargin'!$B$10) | F9: =E9
A10: Annual Recurring (per year) | B10: ='02_HoursByPhase'!I14 | C10: ='03_CalculatedCost'!I14 | D10: =C10*(1-'04_Discounts'!$D$13) | E10: =D10*(1+'05_RiskMargin'!$B$11) | F10: =E10
A12: YEAR 1 INITIAL DELIVERY (Phases 1-4 only) | B12: =SUM(B5:B8) | F12: =SUM(F5:F8)
A13: YEAR 2 ONGOING (12 x SS) + Annual | B13: =12*B9+B10 | F13: =12*F9+F10
